tracardi_cli/__init__.py
tracardi_cli/main.py
tracardi_cli/plugin_scaffold.zip
tracardi_cli-1.3.dist-info/METADATA
tracardi_cli-1.3.dist-info/WHEEL
tracardi_cli-1.3.dist-info/entry_points.txt
tracardi_cli-1.3.dist-info/top_level.txt
tracardi_cli-1.3.dist-info/RECORD
