Metadata-Version: 2.1
Name: tracardi-cli
Version: 1.3
Summary: This is tracardi CLI.
Home-page: UNKNOWN
Author: Risto Kowaczewski
License: UNKNOWN
Platform: UNKNOWN
Requires-Python: >=3.5
Requires-Dist: setuptools
Requires-Dist: argparse
Requires-Dist: jinja2
